aliyunsdkebs/__init__.py
aliyunsdkebs/request/__init__.py
aliyunsdkebs/request/v20210730/AddDiskReplicaPairRequest.py
aliyunsdkebs/request/v20210730/CreateDedicatedBlockStorageClusterRequest.py
aliyunsdkebs/request/v20210730/CreateDiskReplicaGroupRequest.py
aliyunsdkebs/request/v20210730/CreateDiskReplicaPairRequest.py
aliyunsdkebs/request/v20210730/DeleteDiskReplicaGroupRequest.py
aliyunsdkebs/request/v20210730/DeleteDiskReplicaPairRequest.py
aliyunsdkebs/request/v20210730/DescribeDedicatedBlockStorageClusterDisksRequest.py
aliyunsdkebs/request/v20210730/DescribeDedicatedBlockStorageClustersRequest.py
aliyunsdkebs/request/v20210730/DescribeDiskReplicaGroupsRequest.py
aliyunsdkebs/request/v20210730/DescribeDiskReplicaPairsRequest.py
aliyunsdkebs/request/v20210730/DescribeRegionsRequest.py
aliyunsdkebs/request/v20210730/FailoverDiskReplicaGroupRequest.py
aliyunsdkebs/request/v20210730/FailoverDiskReplicaPairRequest.py
aliyunsdkebs/request/v20210730/ModifyDedicatedBlockStorageClusterAttributeRequest.py
aliyunsdkebs/request/v20210730/ModifyDiskReplicaGroupRequest.py
aliyunsdkebs/request/v20210730/ModifyDiskReplicaPairRequest.py
aliyunsdkebs/request/v20210730/RemoveDiskReplicaPairRequest.py
aliyunsdkebs/request/v20210730/ReprotectDiskReplicaGroupRequest.py
aliyunsdkebs/request/v20210730/ReprotectDiskReplicaPairRequest.py
aliyunsdkebs/request/v20210730/StartDiskReplicaGroupRequest.py
aliyunsdkebs/request/v20210730/StartDiskReplicaPairRequest.py
aliyunsdkebs/request/v20210730/StopDiskReplicaGroupRequest.py
aliyunsdkebs/request/v20210730/StopDiskReplicaPairRequest.py
aliyunsdkebs/request/v20210730/__init__.py
aliyun_python_sdk_ebs-1.3.7.dist-info/LICENSE
aliyun_python_sdk_ebs-1.3.7.dist-info/METADATA
aliyun_python_sdk_ebs-1.3.7.dist-info/WHEEL
aliyun_python_sdk_ebs-1.3.7.dist-info/top_level.txt
aliyun_python_sdk_ebs-1.3.7.dist-info/RECORD
